[
  {
    "time": "00:00",
    "value": 38.8
  },
  {
    "time": "01:00",
    "value": 38.1
  },
  {
    "time": "02:00",
    "value": 48.8
  },
  {
    "time": "03:00",
    "value": 51.6
  },
  {
    "time": "04:00",
    "value": 40.1
  },
  {
    "time": "05:00",
    "value": 42.9
  },
  {
    "time": "06:00",
    "value": 47.1
  },
  {
    "time": "07:00",
    "value": 45.4
  },
  {
    "time": "08:00",
    "value": 42.7
  },
  {
    "time": "09:00",
    "value": 46
  },
  {
    "time": "10:00",
    "value": 47.5
  },
  {
    "time": "11:00",
    "value": 38.8
  },
  {
    "time": "12:00",
    "value": 50.1
  },
  {
    "time": "13:00",
    "value": 52.8
  },
  {
    "time": "14:00",
    "value": 35.3
  },
  {
    "time": "15:00",
    "value": 30
  },
  {
    "time": "16:00",
    "value": 38.3
  },
  {
    "time": "17:00",
    "value": 46.5
  },
  {
    "time": "18:00",
    "value": 44.4
  },
  {
    "time": "19:00",
    "value": 43.4
  },
  {
    "time": "20:00",
    "value": 46.4
  },
  {
    "time": "21:00",
    "value": 41.2
  },
  {
    "time": "22:00",
    "value": 48.4
  },
  {
    "time": "23:00",
    "value": 44.8
  },
  {
    "time": "00:00",
    "value": 44.7
  },
  {
    "time": "01:00",
    "value": 48.9
  },
  {
    "time": "02:00",
    "value": 31.6
  },
  {
    "time": "03:00",
    "value": 49.3
  },
  {
    "time": "04:00",
    "value": 45.7
  },
  {
    "time": "05:00",
    "value": 32.9
  },
  {
    "time": "06:00",
    "value": 40
  },
  {
    "time": "07:00",
    "value": 44.5
  },
  {
    "time": "08:00",
    "value": 41.2
  },
  {
    "time": "09:00",
    "value": 31.9
  },
  {
    "time": "10:00",
    "value": 37
  },
  {
    "time": "11:00",
    "value": 41.8
  },
  {
    "time": "12:00",
    "value": 44.3
  },
  {
    "time": "13:00",
    "value": 45
  },
  {
    "time": "14:00",
    "value": 43.5
  },
  {
    "time": "15:00",
    "value": 41
  },
  {
    "time": "16:00",
    "value": 42.1
  },
  {
    "time": "17:00",
    "value": 46
  },
  {
    "time": "18:00",
    "value": 37.7
  },
  {
    "time": "19:00",
    "value": 45
  },
  {
    "time": "20:00",
    "value": 42.7
  },
  {
    "time": "21:00",
    "value": 46.3
  },
  {
    "time": "22:00",
    "value": 45.4
  },
  {
    "time": "23:00",
    "value": 42.3
  },
  {
    "time": "00:00",
    "value": 50.1
  },
  {
    "time": "01:00",
    "value": 51.4
  },
  {
    "time": "02:00",
    "value": 41.8
  },
  {
    "time": "03:00",
    "value": 46.1
  },
  {
    "time": "04:00",
    "value": 47
  },
  {
    "time": "05:00",
    "value": 42.6
  },
  {
    "time": "06:00",
    "value": 46.9
  },
  {
    "time": "07:00",
    "value": 37.6
  },
  {
    "time": "08:00",
    "value": 40.2
  },
  {
    "time": "09:00",
    "value": 35.7
  },
  {
    "time": "10:00",
    "value": 42.1
  },
  {
    "time": "11:00",
    "value": 47.5
  },
  {
    "time": "12:00",
    "value": 44.9
  },
  {
    "time": "13:00",
    "value": 39.6
  },
  {
    "time": "14:00",
    "value": 47.6
  },
  {
    "time": "15:00",
    "value": 44.8
  },
  {
    "time": "16:00",
    "value": 44.6
  },
  {
    "time": "17:00",
    "value": 40.4
  },
  {
    "time": "18:00",
    "value": 41
  },
  {
    "time": "19:00",
    "value": 42.5
  },
  {
    "time": "20:00",
    "value": 48
  },
  {
    "time": "21:00",
    "value": 48.2
  },
  {
    "time": "22:00",
    "value": 39.4
  },
  {
    "time": "23:00",
    "value": 47
  },
  {
    "time": "00:00",
    "value": 43.5
  },
  {
    "time": "01:00",
    "value": 52.6
  },
  {
    "time": "02:00",
    "value": 42.6
  },
  {
    "time": "03:00",
    "value": 37.7
  },
  {
    "time": "04:00",
    "value": 38.6
  },
  {
    "time": "05:00",
    "value": 43.8
  },
  {
    "time": "06:00",
    "value": 39.1
  },
  {
    "time": "07:00",
    "value": 41.1
  },
  {
    "time": "08:00",
    "value": 39.1
  },
  {
    "time": "09:00",
    "value": 47.8
  },
  {
    "time": "10:00",
    "value": 43.8
  },
  {
    "time": "11:00",
    "value": 39.3
  },
  {
    "time": "12:00",
    "value": 50.9
  },
  {
    "time": "13:00",
    "value": 47.2
  },
  {
    "time": "14:00",
    "value": 40.9
  },
  {
    "time": "15:00",
    "value": 40.4
  },
  {
    "time": "16:00",
    "value": 44.2
  },
  {
    "time": "17:00",
    "value": 46.3
  },
  {
    "time": "18:00",
    "value": 51.9
  },
  {
    "time": "19:00",
    "value": 37.6
  },
  {
    "time": "20:00",
    "value": 33.9
  },
  {
    "time": "21:00",
    "value": 37.4
  },
  {
    "time": "22:00",
    "value": 37.2
  },
  {
    "time": "23:00",
    "value": 39.1
  },
  {
    "time": "00:00",
    "value": 38.5
  },
  {
    "time": "01:00",
    "value": 43.9
  },
  {
    "time": "02:00",
    "value": 46
  },
  {
    "time": "03:00",
    "value": 40.6
  },
  {
    "time": "04:00",
    "value": 41.1
  },
  {
    "time": "05:00",
    "value": 50
  },
  {
    "time": "06:00",
    "value": 42.2
  },
  {
    "time": "07:00",
    "value": 48.7
  },
  {
    "time": "08:00",
    "value": 35.6
  },
  {
    "time": "09:00",
    "value": 41.8
  },
  {
    "time": "10:00",
    "value": 31.3
  },
  {
    "time": "11:00",
    "value": 45.2
  },
  {
    "time": "12:00",
    "value": 44.1
  },
  {
    "time": "13:00",
    "value": 50.3
  },
  {
    "time": "14:00",
    "value": 47.6
  },
  {
    "time": "15:00",
    "value": 44.2
  },
  {
    "time": "16:00",
    "value": 43.8
  },
  {
    "time": "17:00",
    "value": 44.1
  },
  {
    "time": "18:00",
    "value": 43.2
  },
  {
    "time": "19:00",
    "value": 44.8
  },
  {
    "time": "20:00",
    "value": 42.7
  },
  {
    "time": "21:00",
    "value": 44.8
  },
  {
    "time": "22:00",
    "value": 44.8
  },
  {
    "time": "23:00",
    "value": 39.7
  },
  {
    "time": "00:00",
    "value": 47.4
  },
  {
    "time": "01:00",
    "value": 33.9
  },
  {
    "time": "02:00",
    "value": 48.5
  },
  {
    "time": "03:00",
    "value": 31.9
  },
  {
    "time": "04:00",
    "value": 43.5
  },
  {
    "time": "05:00",
    "value": 40.3
  },
  {
    "time": "06:00",
    "value": 39
  },
  {
    "time": "07:00",
    "value": 46.7
  },
  {
    "time": "08:00",
    "value": 52.9
  },
  {
    "time": "09:00",
    "value": 37.8
  },
  {
    "time": "10:00",
    "value": 45.1
  },
  {
    "time": "11:00",
    "value": 44.1
  },
  {
    "time": "12:00",
    "value": 42.7
  },
  {
    "time": "13:00",
    "value": 42
  },
  {
    "time": "14:00",
    "value": 35.2
  },
  {
    "time": "15:00",
    "value": 43.9
  },
  {
    "time": "16:00",
    "value": 55.2
  },
  {
    "time": "17:00",
    "value": 51.7
  },
  {
    "time": "18:00",
    "value": 48.9
  },
  {
    "time": "19:00",
    "value": 39.9
  },
  {
    "time": "20:00",
    "value": 38.2
  },
  {
    "time": "21:00",
    "value": 44.1
  },
  {
    "time": "22:00",
    "value": 52.2
  },
  {
    "time": "23:00",
    "value": 43.7
  },
  {
    "time": "00:00",
    "value": 37
  },
  {
    "time": "01:00",
    "value": 44.1
  },
  {
    "time": "02:00",
    "value": 40.8
  },
  {
    "time": "03:00",
    "value": 41.4
  },
  {
    "time": "04:00",
    "value": 39.8
  },
  {
    "time": "05:00",
    "value": 43.4
  },
  {
    "time": "06:00",
    "value": 44.5
  },
  {
    "time": "07:00",
    "value": 40.7
  },
  {
    "time": "08:00",
    "value": 45.3
  },
  {
    "time": "09:00",
    "value": 41.6
  },
  {
    "time": "10:00",
    "value": 36.7
  },
  {
    "time": "11:00",
    "value": 45.8
  },
  {
    "time": "12:00",
    "value": 39.8
  },
  {
    "time": "13:00",
    "value": 46.8
  },
  {
    "time": "14:00",
    "value": 40.8
  },
  {
    "time": "15:00",
    "value": 43.6
  },
  {
    "time": "16:00",
    "value": 55
  },
  {
    "time": "17:00",
    "value": 37.1
  },
  {
    "time": "18:00",
    "value": 44.5
  },
  {
    "time": "19:00",
    "value": 45.7
  },
  {
    "time": "20:00",
    "value": 48
  },
  {
    "time": "21:00",
    "value": 47.6
  },
  {
    "time": "22:00",
    "value": 46.8
  },
  {
    "time": "23:00",
    "value": 39.6
  }
]
